duckduckai/__init__.py
duckduckai/ask_chat.py
DuckDuckAI-1.0.3.dist-info/METADATA
DuckDuckAI-1.0.3.dist-info/WHEEL
DuckDuckAI-1.0.3.dist-info/top_level.txt
DuckDuckAI-1.0.3.dist-info/RECORD
