Metadata-Version: 2.2
Name: DuckDuckAI
Version: 1.0.3
Summary: A package to interact with DuckDuckGo AI-powered search
Home-page: https://github.com/ramona-flower/DuckDuckAI
Author: Ramona-Flower
Classifier: Programming Language :: Python :: 3
Classifier: License :: OSI Approved :: MIT License
Classifier: Operating System :: OS Independent
Requires-Python: >=3.6
Requires-Dist: requests
Dynamic: author
Dynamic: classifier
Dynamic: description
Dynamic: description-content-type
Dynamic: home-page
Dynamic: requires-dist
Dynamic: requires-python
Dynamic: summary
